assign_overload/__init__.py
assign_overload/magic.py
assign_overload/patch.py
assign_overload/transformer.py
assign_overload-1.0.3.dist-info/METADATA
assign_overload-1.0.3.dist-info/WHEEL
assign_overload-1.0.3.dist-info/RECORD
