Metadata-Version: 2.4
Name: assign-overload
Version: 1.0.3
Summary: overloading assignment operator everywhere
Project-URL: Homepage, https://github.com/pyhacks/assign-overload
Author-email: pyhacks <enginyildirim111@gmail.com>
Keywords: assign,assignment,magic,method,operator,overloading
